[
  {
    "ticker": "TQQQ",
    "fund_name": "Direxion Daily NASDAQ-100 Bull 3X Shares",
    "isin": "N/A",
    "cusip": "N/A",
    "inception_date": "2025-11-29",
    "nav_amount": "0.00",
    "nav_as_of": "2025-11-29",
    "expense_ratio": "0.00",
    "ytd_return": null,
    "one_year_return": null,
    "three_year_return": null,
    "five_year_return": null,
    "ten_year_return": null,
    "since_inception_return": null,
    "asset_class": "Leveraged/Inverse",
    "region": "US",
    "market_type": "ETF",
    "distribution_yield": null,
    "distribution_frequency": "Unknown",
    "product_page_url": "https://www.direxion.com/product/tqqq",
    "detail_page_url": "https://www.direxion.com/product/tqqq"
  },
  {
    "ticker": "SOXL",
    "fund_name": "Direxion Daily Semiconductor Bull 3X Shares",
    "isin": "N/A",
    "cusip": "N/A",
    "inception_date": "2025-11-29",
    "nav_amount": "0.00",
    "nav_as_of": "2025-11-29",
    "expense_ratio": "0.00",
    "ytd_return": null,
    "one_year_return": null,
    "three_year_return": null,
    "five_year_return": null,
    "ten_year_return": null,
    "since_inception_return": null,
    "asset_class": "Leveraged/Inverse",
    "region": "US",
    "market_type": "ETF",
    "distribution_yield": null,
    "distribution_frequency": "Unknown",
    "product_page_url": "https://www.direxion.com/product/soxl",
    "detail_page_url": "https://www.direxion.com/product/soxl"
  },
  {
    "ticker": "SPXL",
    "fund_name": "Direxion Daily S&P 500 Bull 3X Shares",
    "isin": "N/A",
    "cusip": "N/A",
    "inception_date": "2025-11-29",
    "nav_amount": "0.00",
    "nav_as_of": "2025-11-29",
    "expense_ratio": "0.00",
    "ytd_return": null,
    "one_year_return": null,
    "three_year_return": null,
    "five_year_return": null,
    "ten_year_return": null,
    "since_inception_return": null,
    "asset_class": "Leveraged/Inverse",
    "region": "US",
    "market_type": "ETF",
    "distribution_yield": null,
    "distribution_frequency": "Unknown",
    "product_page_url": "https://www.direxion.com/product/spxl",
    "detail_page_url": "https://www.direxion.com/product/spxl"
  },
  {
    "ticker": "TNA",
    "fund_name": "Direxion Daily Small Cap Bull 3X Shares",
    "isin": "N/A",
    "cusip": "N/A",
    "inception_date": "2025-11-29",
    "nav_amount": "0.00",
    "nav_as_of": "2025-11-29",
    "expense_ratio": "0.00",
    "ytd_return": null,
    "one_year_return": null,
    "three_year_return": null,
    "five_year_return": null,
    "ten_year_return": null,
    "since_inception_return": null,
    "asset_class": "Leveraged/Inverse",
    "region": "US",
    "market_type": "ETF",
    "distribution_yield": null,
    "distribution_frequency": "Unknown",
    "product_page_url": "https://www.direxion.com/product/tna",
    "detail_page_url": "https://www.direxion.com/product/tna"
  },
  {
    "ticker": "TECL",
    "fund_name": "Direxion Daily Technology Bull 3X Shares",
    "isin": "N/A",
    "cusip": "N/A",
    "inception_date": "2025-11-29",
    "nav_amount": "0.00",
    "nav_as_of": "2025-11-29",
    "expense_ratio": "0.00",
    "ytd_return": null,
    "one_year_return": null,
    "three_year_return": null,
    "five_year_return": null,
    "ten_year_return": null,
    "since_inception_return": null,
    "asset_class": "Leveraged/Inverse",
    "region": "US",
    "market_type": "ETF",
    "distribution_yield": null,
    "distribution_frequency": "Unknown",
    "product_page_url": "https://www.direxion.com/product/tecl",
    "detail_page_url": "https://www.direxion.com/product/tecl"
  },
  {
    "ticker": "CURE",
    "fund_name": "Direxion Daily Healthcare Bull 3X Shares",
    "isin": "N/A",
    "cusip": "N/A",
    "inception_date": "2025-11-29",
    "nav_amount": "0.00",
    "nav_as_of": "2025-11-29",
    "expense_ratio": "0.00",
    "ytd_return": null,
    "one_year_return": null,
    "three_year_return": null,
    "five_year_return": null,
    "ten_year_return": null,
    "since_inception_return": null,
    "asset_class": "Leveraged/Inverse",
    "region": "US",
    "market_type": "ETF",
    "distribution_yield": null,
    "distribution_frequency": "Unknown",
    "product_page_url": "https://www.direxion.com/product/cure",
    "detail_page_url": "https://www.direxion.com/product/cure"
  },
  {
    "ticker": "DPST",
    "fund_name": "Direxion Daily Regional Banks Bull 3X Shares",
    "isin": "N/A",
    "cusip": "N/A",
    "inception_date": "2025-11-29",
    "nav_amount": "0.00",
    "nav_as_of": "2025-11-29",
    "expense_ratio": "0.00",
    "ytd_return": null,
    "one_year_return": null,
    "three_year_return": null,
    "five_year_return": null,
    "ten_year_return": null,
    "since_inception_return": null,
    "asset_class": "Leveraged/Inverse",
    "region": "US",
    "market_type": "ETF",
    "distribution_yield": null,
    "distribution_frequency": "Unknown",
    "product_page_url": "https://www.direxion.com/product/dpst",
    "detail_page_url": "https://www.direxion.com/product/dpst"
  },
  {
    "ticker": "FAS",
    "fund_name": "Direxion Daily Financial Bull 3X Shares",
    "isin": "N/A",
    "cusip": "N/A",
    "inception_date": "2025-11-29",
    "nav_amount": "0.00",
    "nav_as_of": "2025-11-29",
    "expense_ratio": "0.00",
    "ytd_return": null,
    "one_year_return": null,
    "three_year_return": null,
    "five_year_return": null,
    "ten_year_return": null,
    "since_inception_return": null,
    "asset_class": "Leveraged/Inverse",
    "region": "US",
    "market_type": "ETF",
    "distribution_yield": null,
    "distribution_frequency": "Unknown",
    "product_page_url": "https://www.direxion.com/product/fas",
    "detail_page_url": "https://www.direxion.com/product/fas"
  },
  {
    "ticker": "LABU",
    "fund_name": "Direxion Daily S&P Biotech Bull 3X Shares",
    "isin": "N/A",
    "cusip": "N/A",
    "inception_date": "2025-11-29",
    "nav_amount": "0.00",
    "nav_as_of": "2025-11-29",
    "expense_ratio": "0.00",
    "ytd_return": null,
    "one_year_return": null,
    "three_year_return": null,
    "five_year_return": null,
    "ten_year_return": null,
    "since_inception_return": null,
    "asset_class": "Leveraged/Inverse",
    "region": "US",
    "market_type": "ETF",
    "distribution_yield": null,
    "distribution_frequency": "Unknown",
    "product_page_url": "https://www.direxion.com/product/labu",
    "detail_page_url": "https://www.direxion.com/product/labu"
  },
  {
    "ticker": "NAIL",
    "fund_name": "Direxion Daily Homebuilders & Supplies Bull 3X Shares",
    "isin": "N/A",
    "cusip": "N/A",
    "inception_date": "2025-11-29",
    "nav_amount": "0.00",
    "nav_as_of": "2025-11-29",
    "expense_ratio": "0.00",
    "ytd_return": null,
    "one_year_return": null,
    "three_year_return": null,
    "five_year_return": null,
    "ten_year_return": null,
    "since_inception_return": null,
    "asset_class": "Leveraged/Inverse",
    "region": "US",
    "market_type": "ETF",
    "distribution_yield": null,
    "distribution_frequency": "Unknown",
    "product_page_url": "https://www.direxion.com/product/nail",
    "detail_page_url": "https://www.direxion.com/product/nail"
  },
  {
    "ticker": "WANT",
    "fund_name": "Direxion Daily Consumer Discretionary Bull 3X Shares",
    "isin": "N/A",
    "cusip": "N/A",
    "inception_date": "2025-11-29",
    "nav_amount": "0.00",
    "nav_as_of": "2025-11-29",
    "expense_ratio": "0.00",
    "ytd_return": null,
    "one_year_return": null,
    "three_year_return": null,
    "five_year_return": null,
    "ten_year_return": null,
    "since_inception_return": null,
    "asset_class": "Leveraged/Inverse",
    "region": "US",
    "market_type": "ETF",
    "distribution_yield": null,
    "distribution_frequency": "Unknown",
    "product_page_url": "https://www.direxion.com/product/want",
    "detail_page_url": "https://www.direxion.com/product/want"
  },
  {
    "ticker": "UTSL",
    "fund_name": "Direxion Daily Utilities Bull 3X Shares",
    "isin": "N/A",
    "cusip": "N/A",
    "inception_date": "2025-11-29",
    "nav_amount": "0.00",
    "nav_as_of": "2025-11-29",
    "expense_ratio": "0.00",
    "ytd_return": null,
    "one_year_return": null,
    "three_year_return": null,
    "five_year_return": null,
    "ten_year_return": null,
    "since_inception_return": null,
    "asset_class": "Leveraged/Inverse",
    "region": "US",
    "market_type": "ETF",
    "distribution_yield": null,
    "distribution_frequency": "Unknown",
    "product_page_url": "https://www.direxion.com/product/utsl",
    "detail_page_url": "https://www.direxion.com/product/utsl"
  },
  {
    "ticker": "ERX",
    "fund_name": "Direxion Daily Energy Bull 2X Shares",
    "isin": "N/A",
    "cusip": "N/A",
    "inception_date": "2025-11-29",
    "nav_amount": "0.00",
    "nav_as_of": "2025-11-29",
    "expense_ratio": "0.00",
    "ytd_return": null,
    "one_year_return": null,
    "three_year_return": null,
    "five_year_return": null,
    "ten_year_return": null,
    "since_inception_return": null,
    "asset_class": "Leveraged/Inverse",
    "region": "US",
    "market_type": "ETF",
    "distribution_yield": null,
    "distribution_frequency": "Unknown",
    "product_page_url": "https://www.direxion.com/product/erx",
    "detail_page_url": "https://www.direxion.com/product/erx"
  },
  {
    "ticker": "RETL",
    "fund_name": "Direxion Daily Retail Bull 3X Shares",
    "isin": "N/A",
    "cusip": "N/A",
    "inception_date": "2025-11-29",
    "nav_amount": "0.00",
    "nav_as_of": "2025-11-29",
    "expense_ratio": "0.00",
    "ytd_return": null,
    "one_year_return": null,
    "three_year_return": null,
    "five_year_return": null,
    "ten_year_return": null,
    "since_inception_return": null,
    "asset_class": "Leveraged/Inverse",
    "region": "US",
    "market_type": "ETF",
    "distribution_yield": null,
    "distribution_frequency": "Unknown",
    "product_page_url": "https://www.direxion.com/product/retl",
    "detail_page_url": "https://www.direxion.com/product/retl"
  },
  {
    "ticker": "DFEN",
    "fund_name": "Direxion Daily Aerospace & Defense Bull 3X Shares",
    "isin": "N/A",
    "cusip": "N/A",
    "inception_date": "2025-11-29",
    "nav_amount": "0.00",
    "nav_as_of": "2025-11-29",
    "expense_ratio": "0.00",
    "ytd_return": null,
    "one_year_return": null,
    "three_year_return": null,
    "five_year_return": null,
    "ten_year_return": null,
    "since_inception_return": null,
    "asset_class": "Leveraged/Inverse",
    "region": "US",
    "market_type": "ETF",
    "distribution_yield": null,
    "distribution_frequency": "Unknown",
    "product_page_url": "https://www.direxion.com/product/dfen",
    "detail_page_url": "https://www.direxion.com/product/dfen"
  },
  {
    "ticker": "PILL",
    "fund_name": "Direxion Daily Pharmaceutical & Medical Bull 3X Shares",
    "isin": "N/A",
    "cusip": "N/A",
    "inception_date": "2025-11-29",
    "nav_amount": "0.00",
    "nav_as_of": "2025-11-29",
    "expense_ratio": "0.00",
    "ytd_return": null,
    "one_year_return": null,
    "three_year_return": null,
    "five_year_return": null,
    "ten_year_return": null,
    "since_inception_return": null,
    "asset_class": "Leveraged/Inverse",
    "region": "US",
    "market_type": "ETF",
    "distribution_yield": null,
    "distribution_frequency": "Unknown",
    "product_page_url": "https://www.direxion.com/product/pill",
    "detail_page_url": "https://www.direxion.com/product/pill"
  },
  {
    "ticker": "HIBL",
    "fund_name": "Direxion Daily S&P 500 High Beta Bull 3X Shares",
    "isin": "N/A",
    "cusip": "N/A",
    "inception_date": "2025-11-29",
    "nav_amount": "0.00",
    "nav_as_of": "2025-11-29",
    "expense_ratio": "0.00",
    "ytd_return": null,
    "one_year_return": null,
    "three_year_return": null,
    "five_year_return": null,
    "ten_year_return": null,
    "since_inception_return": null,
    "asset_class": "Leveraged/Inverse",
    "region": "US",
    "market_type": "ETF",
    "distribution_yield": null,
    "distribution_frequency": "Unknown",
    "product_page_url": "https://www.direxion.com/product/hibl",
    "detail_page_url": "https://www.direxion.com/product/hibl"
  },
  {
    "ticker": "DUSL",
    "fund_name": "Direxion Daily Industrials Bull 3X Shares",
    "isin": "N/A",
    "cusip": "N/A",
    "inception_date": "2025-11-29",
    "nav_amount": "0.00",
    "nav_as_of": "2025-11-29",
    "expense_ratio": "0.00",
    "ytd_return": null,
    "one_year_return": null,
    "three_year_return": null,
    "five_year_return": null,
    "ten_year_return": null,
    "since_inception_return": null,
    "asset_class": "Leveraged/Inverse",
    "region": "US",
    "market_type": "ETF",
    "distribution_yield": null,
    "distribution_frequency": "Unknown",
    "product_page_url": "https://www.direxion.com/product/dusl",
    "detail_page_url": "https://www.direxion.com/product/dusl"
  },
  {
    "ticker": "SQQQ",
    "fund_name": "Direxion Daily NASDAQ-100 Bear 3X Shares",
    "isin": "N/A",
    "cusip": "N/A",
    "inception_date": "2025-11-29",
    "nav_amount": "0.00",
    "nav_as_of": "2025-11-29",
    "expense_ratio": "0.00",
    "ytd_return": null,
    "one_year_return": null,
    "three_year_return": null,
    "five_year_return": null,
    "ten_year_return": null,
    "since_inception_return": null,
    "asset_class": "Leveraged/Inverse",
    "region": "US",
    "market_type": "ETF",
    "distribution_yield": null,
    "distribution_frequency": "Unknown",
    "product_page_url": "https://www.direxion.com/product/sqqq",
    "detail_page_url": "https://www.direxion.com/product/sqqq"
  },
  {
    "ticker": "SOXS",
    "fund_name": "Direxion Daily Semiconductor Bear 3X Shares",
    "isin": "N/A",
    "cusip": "N/A",
    "inception_date": "2025-11-29",
    "nav_amount": "0.00",
    "nav_as_of": "2025-11-29",
    "expense_ratio": "0.00",
    "ytd_return": null,
    "one_year_return": null,
    "three_year_return": null,
    "five_year_return": null,
    "ten_year_return": null,
    "since_inception_return": null,
    "asset_class": "Leveraged/Inverse",
    "region": "US",
    "market_type": "ETF",
    "distribution_yield": null,
    "distribution_frequency": "Unknown",
    "product_page_url": "https://www.direxion.com/product/soxs",
    "detail_page_url": "https://www.direxion.com/product/soxs"
  },
  {
    "ticker": "SPXS",
    "fund_name": "Direxion Daily S&P 500 Bear 3X Shares",
    "isin": "N/A",
    "cusip": "N/A",
    "inception_date": "2025-11-29",
    "nav_amount": "0.00",
    "nav_as_of": "2025-11-29",
    "expense_ratio": "0.00",
    "ytd_return": null,
    "one_year_return": null,
    "three_year_return": null,
    "five_year_return": null,
    "ten_year_return": null,
    "since_inception_return": null,
    "asset_class": "Leveraged/Inverse",
    "region": "US",
    "market_type": "ETF",
    "distribution_yield": null,
    "distribution_frequency": "Unknown",
    "product_page_url": "https://www.direxion.com/product/spxs",
    "detail_page_url": "https://www.direxion.com/product/spxs"
  },
  {
    "ticker": "TZA",
    "fund_name": "Direxion Daily Small Cap Bear 3X Shares",
    "isin": "N/A",
    "cusip": "N/A",
    "inception_date": "2025-11-29",
    "nav_amount": "0.00",
    "nav_as_of": "2025-11-29",
    "expense_ratio": "0.00",
    "ytd_return": null,
    "one_year_return": null,
    "three_year_return": null,
    "five_year_return": null,
    "ten_year_return": null,
    "since_inception_return": null,
    "asset_class": "Leveraged/Inverse",
    "region": "US",
    "market_type": "ETF",
    "distribution_yield": null,
    "distribution_frequency": "Unknown",
    "product_page_url": "https://www.direxion.com/product/tza",
    "detail_page_url": "https://www.direxion.com/product/tza"
  },
  {
    "ticker": "TECS",
    "fund_name": "Direxion Daily Technology Bear 3X Shares",
    "isin": "N/A",
    "cusip": "N/A",
    "inception_date": "2025-11-29",
    "nav_amount": "0.00",
    "nav_as_of": "2025-11-29",
    "expense_ratio": "0.00",
    "ytd_return": null,
    "one_year_return": null,
    "three_year_return": null,
    "five_year_return": null,
    "ten_year_return": null,
    "since_inception_return": null,
    "asset_class": "Leveraged/Inverse",
    "region": "US",
    "market_type": "ETF",
    "distribution_yield": null,
    "distribution_frequency": "Unknown",
    "product_page_url": "https://www.direxion.com/product/tecs",
    "detail_page_url": "https://www.direxion.com/product/tecs"
  },
  {
    "ticker": "FAZ",
    "fund_name": "Direxion Daily Financial Bear 3X Shares",
    "isin": "N/A",
    "cusip": "N/A",
    "inception_date": "2025-11-29",
    "nav_amount": "0.00",
    "nav_as_of": "2025-11-29",
    "expense_ratio": "0.00",
    "ytd_return": null,
    "one_year_return": null,
    "three_year_return": null,
    "five_year_return": null,
    "ten_year_return": null,
    "since_inception_return": null,
    "asset_class": "Leveraged/Inverse",
    "region": "US",
    "market_type": "ETF",
    "distribution_yield": null,
    "distribution_frequency": "Unknown",
    "product_page_url": "https://www.direxion.com/product/faz",
    "detail_page_url": "https://www.direxion.com/product/faz"
  },
  {
    "ticker": "LABD",
    "fund_name": "Direxion Daily S&P Biotech Bear 3X Shares",
    "isin": "N/A",
    "cusip": "N/A",
    "inception_date": "2025-11-29",
    "nav_amount": "0.00",
    "nav_as_of": "2025-11-29",
    "expense_ratio": "0.00",
    "ytd_return": null,
    "one_year_return": null,
    "three_year_return": null,
    "five_year_return": null,
    "ten_year_return": null,
    "since_inception_return": null,
    "asset_class": "Leveraged/Inverse",
    "region": "US",
    "market_type": "ETF",
    "distribution_yield": null,
    "distribution_frequency": "Unknown",
    "product_page_url": "https://www.direxion.com/product/labd",
    "detail_page_url": "https://www.direxion.com/product/labd"
  },
  {
    "ticker": "DRV",
    "fund_name": "Direxion Daily Real Estate Bear 3X Shares",
    "isin": "N/A",
    "cusip": "N/A",
    "inception_date": "2025-11-29",
    "nav_amount": "0.00",
    "nav_as_of": "2025-11-29",
    "expense_ratio": "0.00",
    "ytd_return": null,
    "one_year_return": null,
    "three_year_return": null,
    "five_year_return": null,
    "ten_year_return": null,
    "since_inception_return": null,
    "asset_class": "Leveraged/Inverse",
    "region": "US",
    "market_type": "ETF",
    "distribution_yield": null,
    "distribution_frequency": "Unknown",
    "product_page_url": "https://www.direxion.com/product/drv",
    "detail_page_url": "https://www.direxion.com/product/drv"
  },
  {
    "ticker": "SPDN",
    "fund_name": "Direxion Daily S&P 500 Bear 1X Shares",
    "isin": "N/A",
    "cusip": "N/A",
    "inception_date": "2025-11-29",
    "nav_amount": "0.00",
    "nav_as_of": "2025-11-29",
    "expense_ratio": "0.00",
    "ytd_return": null,
    "one_year_return": null,
    "three_year_return": null,
    "five_year_return": null,
    "ten_year_return": null,
    "since_inception_return": null,
    "asset_class": "Leveraged/Inverse",
    "region": "US",
    "market_type": "ETF",
    "distribution_yield": null,
    "distribution_frequency": "Unknown",
    "product_page_url": "https://www.direxion.com/product/spdn",
    "detail_page_url": "https://www.direxion.com/product/spdn"
  },
  {
    "ticker": "NVDU",
    "fund_name": "Direxion Daily NVDA Bull 2X Shares",
    "isin": "N/A",
    "cusip": "N/A",
    "inception_date": "2025-11-29",
    "nav_amount": "0.00",
    "nav_as_of": "2025-11-29",
    "expense_ratio": "0.00",
    "ytd_return": null,
    "one_year_return": null,
    "three_year_return": null,
    "five_year_return": null,
    "ten_year_return": null,
    "since_inception_return": null,
    "asset_class": "Leveraged/Inverse",
    "region": "US",
    "market_type": "ETF",
    "distribution_yield": null,
    "distribution_frequency": "Unknown",
    "product_page_url": "https://www.direxion.com/product/nvdu",
    "detail_page_url": "https://www.direxion.com/product/nvdu"
  },
  {
    "ticker": "NVDD",
    "fund_name": "Direxion Daily NVDA Bear 1X Shares",
    "isin": "N/A",
    "cusip": "N/A",
    "inception_date": "2025-11-29",
    "nav_amount": "0.00",
    "nav_as_of": "2025-11-29",
    "expense_ratio": "0.00",
    "ytd_return": null,
    "one_year_return": null,
    "three_year_return": null,
    "five_year_return": null,
    "ten_year_return": null,
    "since_inception_return": null,
    "asset_class": "Leveraged/Inverse",
    "region": "US",
    "market_type": "ETF",
    "distribution_yield": null,
    "distribution_frequency": "Unknown",
    "product_page_url": "https://www.direxion.com/product/nvdd",
    "detail_page_url": "https://www.direxion.com/product/nvdd"
  },
  {
    "ticker": "TSLQ",
    "fund_name": "Direxion Daily TSLA Bear 1X Shares",
    "isin": "N/A",
    "cusip": "N/A",
    "inception_date": "2025-11-29",
    "nav_amount": "0.00",
    "nav_as_of": "2025-11-29",
    "expense_ratio": "0.00",
    "ytd_return": null,
    "one_year_return": null,
    "three_year_return": null,
    "five_year_return": null,
    "ten_year_return": null,
    "since_inception_return": null,
    "asset_class": "Leveraged/Inverse",
    "region": "US",
    "market_type": "ETF",
    "distribution_yield": null,
    "distribution_frequency": "Unknown",
    "product_page_url": "https://www.direxion.com/product/tslq",
    "detail_page_url": "https://www.direxion.com/product/tslq"
  },
  {
    "ticker": "TSLL",
    "fund_name": "Direxion Daily TSLA Bull 2X Shares",
    "isin": "N/A",
    "cusip": "N/A",
    "inception_date": "2025-11-29",
    "nav_amount": "0.00",
    "nav_as_of": "2025-11-29",
    "expense_ratio": "0.00",
    "ytd_return": null,
    "one_year_return": null,
    "three_year_return": null,
    "five_year_return": null,
    "ten_year_return": null,
    "since_inception_return": null,
    "asset_class": "Leveraged/Inverse",
    "region": "US",
    "market_type": "ETF",
    "distribution_yield": null,
    "distribution_frequency": "Unknown",
    "product_page_url": "https://www.direxion.com/product/tsll",
    "detail_page_url": "https://www.direxion.com/product/tsll"
  },
  {
    "ticker": "GOOU",
    "fund_name": "Direxion Daily GOOGL Bull 2X Shares",
    "isin": "N/A",
    "cusip": "N/A",
    "inception_date": "2025-11-29",
    "nav_amount": "0.00",
    "nav_as_of": "2025-11-29",
    "expense_ratio": "0.00",
    "ytd_return": null,
    "one_year_return": null,
    "three_year_return": null,
    "five_year_return": null,
    "ten_year_return": null,
    "since_inception_return": null,
    "asset_class": "Leveraged/Inverse",
    "region": "US",
    "market_type": "ETF",
    "distribution_yield": null,
    "distribution_frequency": "Unknown",
    "product_page_url": "https://www.direxion.com/product/goou",
    "detail_page_url": "https://www.direxion.com/product/goou"
  },
  {
    "ticker": "GOOD",
    "fund_name": "Direxion Daily GOOGL Bear 1X Shares",
    "isin": "N/A",
    "cusip": "N/A",
    "inception_date": "2025-11-29",
    "nav_amount": "0.00",
    "nav_as_of": "2025-11-29",
    "expense_ratio": "0.00",
    "ytd_return": null,
    "one_year_return": null,
    "three_year_return": null,
    "five_year_return": null,
    "ten_year_return": null,
    "since_inception_return": null,
    "asset_class": "Leveraged/Inverse",
    "region": "US",
    "market_type": "ETF",
    "distribution_yield": null,
    "distribution_frequency": "Unknown",
    "product_page_url": "https://www.direxion.com/product/good",
    "detail_page_url": "https://www.direxion.com/product/good"
  },
  {
    "ticker": "APLY",
    "fund_name": "Direxion Daily AAPL Bear 1X Shares",
    "isin": "N/A",
    "cusip": "N/A",
    "inception_date": "2025-11-29",
    "nav_amount": "0.00",
    "nav_as_of": "2025-11-29",
    "expense_ratio": "0.00",
    "ytd_return": null,
    "one_year_return": null,
    "three_year_return": null,
    "five_year_return": null,
    "ten_year_return": null,
    "since_inception_return": null,
    "asset_class": "Leveraged/Inverse",
    "region": "US",
    "market_type": "ETF",
    "distribution_yield": null,
    "distribution_frequency": "Unknown",
    "product_page_url": "https://www.direxion.com/product/aply",
    "detail_page_url": "https://www.direxion.com/product/aply"
  },
  {
    "ticker": "AAPU",
    "fund_name": "Direxion Daily AAPL Bull 2X Shares",
    "isin": "N/A",
    "cusip": "N/A",
    "inception_date": "2025-11-29",
    "nav_amount": "0.00",
    "nav_as_of": "2025-11-29",
    "expense_ratio": "0.00",
    "ytd_return": null,
    "one_year_return": null,
    "three_year_return": null,
    "five_year_return": null,
    "ten_year_return": null,
    "since_inception_return": null,
    "asset_class": "Leveraged/Inverse",
    "region": "US",
    "market_type": "ETF",
    "distribution_yield": null,
    "distribution_frequency": "Unknown",
    "product_page_url": "https://www.direxion.com/product/aapu",
    "detail_page_url": "https://www.direxion.com/product/aapu"
  },
  {
    "ticker": "AMZU",
    "fund_name": "Direxion Daily AMZN Bull 2X Shares",
    "isin": "N/A",
    "cusip": "N/A",
    "inception_date": "2025-11-29",
    "nav_amount": "0.00",
    "nav_as_of": "2025-11-29",
    "expense_ratio": "0.00",
    "ytd_return": null,
    "one_year_return": null,
    "three_year_return": null,
    "five_year_return": null,
    "ten_year_return": null,
    "since_inception_return": null,
    "asset_class": "Leveraged/Inverse",
    "region": "US",
    "market_type": "ETF",
    "distribution_yield": null,
    "distribution_frequency": "Unknown",
    "product_page_url": "https://www.direxion.com/product/amzu",
    "detail_page_url": "https://www.direxion.com/product/amzu"
  },
  {
    "ticker": "AMZD",
    "fund_name": "Direxion Daily AMZN Bear 1X Shares",
    "isin": "N/A",
    "cusip": "N/A",
    "inception_date": "2025-11-29",
    "nav_amount": "0.00",
    "nav_as_of": "2025-11-29",
    "expense_ratio": "0.00",
    "ytd_return": null,
    "one_year_return": null,
    "three_year_return": null,
    "five_year_return": null,
    "ten_year_return": null,
    "since_inception_return": null,
    "asset_class": "Leveraged/Inverse",
    "region": "US",
    "market_type": "ETF",
    "distribution_yield": null,
    "distribution_frequency": "Unknown",
    "product_page_url": "https://www.direxion.com/product/amzd",
    "detail_page_url": "https://www.direxion.com/product/amzd"
  },
  {
    "ticker": "MSFU",
    "fund_name": "Direxion Daily MSFT Bull 2X Shares",
    "isin": "N/A",
    "cusip": "N/A",
    "inception_date": "2025-11-29",
    "nav_amount": "0.00",
    "nav_as_of": "2025-11-29",
    "expense_ratio": "0.00",
    "ytd_return": null,
    "one_year_return": null,
    "three_year_return": null,
    "five_year_return": null,
    "ten_year_return": null,
    "since_inception_return": null,
    "asset_class": "Leveraged/Inverse",
    "region": "US",
    "market_type": "ETF",
    "distribution_yield": null,
    "distribution_frequency": "Unknown",
    "product_page_url": "https://www.direxion.com/product/msfu",
    "detail_page_url": "https://www.direxion.com/product/msfu"
  },
  {
    "ticker": "MSFD",
    "fund_name": "Direxion Daily MSFT Bear 1X Shares",
    "isin": "N/A",
    "cusip": "N/A",
    "inception_date": "2025-11-29",
    "nav_amount": "0.00",
    "nav_as_of": "2025-11-29",
    "expense_ratio": "0.00",
    "ytd_return": null,
    "one_year_return": null,
    "three_year_return": null,
    "five_year_return": null,
    "ten_year_return": null,
    "since_inception_return": null,
    "asset_class": "Leveraged/Inverse",
    "region": "US",
    "market_type": "ETF",
    "distribution_yield": null,
    "distribution_frequency": "Unknown",
    "product_page_url": "https://www.direxion.com/product/msfd",
    "detail_page_url": "https://www.direxion.com/product/msfd"
  },
  {
    "ticker": "NFLU",
    "fund_name": "Direxion Daily NFLX Bull 2X Shares",
    "isin": "N/A",
    "cusip": "N/A",
    "inception_date": "2025-11-29",
    "nav_amount": "0.00",
    "nav_as_of": "2025-11-29",
    "expense_ratio": "0.00",
    "ytd_return": null,
    "one_year_return": null,
    "three_year_return": null,
    "five_year_return": null,
    "ten_year_return": null,
    "since_inception_return": null,
    "asset_class": "Leveraged/Inverse",
    "region": "US",
    "market_type": "ETF",
    "distribution_yield": null,
    "distribution_frequency": "Unknown",
    "product_page_url": "https://www.direxion.com/product/nflu",
    "detail_page_url": "https://www.direxion.com/product/nflu"
  },
  {
    "ticker": "NFLD",
    "fund_name": "Direxion Daily NFLX Bear 1X Shares",
    "isin": "N/A",
    "cusip": "N/A",
    "inception_date": "2025-11-29",
    "nav_amount": "0.00",
    "nav_as_of": "2025-11-29",
    "expense_ratio": "0.00",
    "ytd_return": null,
    "one_year_return": null,
    "three_year_return": null,
    "five_year_return": null,
    "ten_year_return": null,
    "since_inception_return": null,
    "asset_class": "Leveraged/Inverse",
    "region": "US",
    "market_type": "ETF",
    "distribution_yield": null,
    "distribution_frequency": "Unknown",
    "product_page_url": "https://www.direxion.com/product/nfld",
    "detail_page_url": "https://www.direxion.com/product/nfld"
  },
  {
    "ticker": "JNUG",
    "fund_name": "Direxion Daily Junior Gold Miners Index Bull 2X Shares",
    "isin": "N/A",
    "cusip": "N/A",
    "inception_date": "2025-11-29",
    "nav_amount": "0.00",
    "nav_as_of": "2025-11-29",
    "expense_ratio": "0.00",
    "ytd_return": null,
    "one_year_return": null,
    "three_year_return": null,
    "five_year_return": null,
    "ten_year_return": null,
    "since_inception_return": null,
    "asset_class": "Leveraged/Inverse",
    "region": "US",
    "market_type": "ETF",
    "distribution_yield": null,
    "distribution_frequency": "Unknown",
    "product_page_url": "https://www.direxion.com/product/jnug",
    "detail_page_url": "https://www.direxion.com/product/jnug"
  },
  {
    "ticker": "JDST",
    "fund_name": "Direxion Daily Junior Gold Miners Index Bear 2X Shares",
    "isin": "N/A",
    "cusip": "N/A",
    "inception_date": "2025-11-29",
    "nav_amount": "0.00",
    "nav_as_of": "2025-11-29",
    "expense_ratio": "0.00",
    "ytd_return": null,
    "one_year_return": null,
    "three_year_return": null,
    "five_year_return": null,
    "ten_year_return": null,
    "since_inception_return": null,
    "asset_class": "Leveraged/Inverse",
    "region": "US",
    "market_type": "ETF",
    "distribution_yield": null,
    "distribution_frequency": "Unknown",
    "product_page_url": "https://www.direxion.com/product/jdst",
    "detail_page_url": "https://www.direxion.com/product/jdst"
  },
  {
    "ticker": "NUGT",
    "fund_name": "Direxion Daily Gold Miners Index Bull 2X Shares",
    "isin": "N/A",
    "cusip": "N/A",
    "inception_date": "2025-11-29",
    "nav_amount": "0.00",
    "nav_as_of": "2025-11-29",
    "expense_ratio": "0.00",
    "ytd_return": null,
    "one_year_return": null,
    "three_year_return": null,
    "five_year_return": null,
    "ten_year_return": null,
    "since_inception_return": null,
    "asset_class": "Leveraged/Inverse",
    "region": "US",
    "market_type": "ETF",
    "distribution_yield": null,
    "distribution_frequency": "Unknown",
    "product_page_url": "https://www.direxion.com/product/nugt",
    "detail_page_url": "https://www.direxion.com/product/nugt"
  },
  {
    "ticker": "DUST",
    "fund_name": "Direxion Daily Gold Miners Index Bear 2X Shares",
    "isin": "N/A",
    "cusip": "N/A",
    "inception_date": "2025-11-29",
    "nav_amount": "0.00",
    "nav_as_of": "2025-11-29",
    "expense_ratio": "0.00",
    "ytd_return": null,
    "one_year_return": null,
    "three_year_return": null,
    "five_year_return": null,
    "ten_year_return": null,
    "since_inception_return": null,
    "asset_class": "Leveraged/Inverse",
    "region": "US",
    "market_type": "ETF",
    "distribution_yield": null,
    "distribution_frequency": "Unknown",
    "product_page_url": "https://www.direxion.com/product/dust",
    "detail_page_url": "https://www.direxion.com/product/dust"
  },
  {
    "ticker": "YINN",
    "fund_name": "Direxion Daily FTSE China Bull 3X Shares",
    "isin": "N/A",
    "cusip": "N/A",
    "inception_date": "2025-11-29",
    "nav_amount": "0.00",
    "nav_as_of": "2025-11-29",
    "expense_ratio": "0.00",
    "ytd_return": null,
    "one_year_return": null,
    "three_year_return": null,
    "five_year_return": null,
    "ten_year_return": null,
    "since_inception_return": null,
    "asset_class": "Leveraged/Inverse",
    "region": "US",
    "market_type": "ETF",
    "distribution_yield": null,
    "distribution_frequency": "Unknown",
    "product_page_url": "https://www.direxion.com/product/yinn",
    "detail_page_url": "https://www.direxion.com/product/yinn"
  },
  {
    "ticker": "YANG",
    "fund_name": "Direxion Daily FTSE China Bear 3X Shares",
    "isin": "N/A",
    "cusip": "N/A",
    "inception_date": "2025-11-29",
    "nav_amount": "0.00",
    "nav_as_of": "2025-11-29",
    "expense_ratio": "0.00",
    "ytd_return": null,
    "one_year_return": null,
    "three_year_return": null,
    "five_year_return": null,
    "ten_year_return": null,
    "since_inception_return": null,
    "asset_class": "Leveraged/Inverse",
    "region": "US",
    "market_type": "ETF",
    "distribution_yield": null,
    "distribution_frequency": "Unknown",
    "product_page_url": "https://www.direxion.com/product/yang",
    "detail_page_url": "https://www.direxion.com/product/yang"
  },
  {
    "ticker": "BRZU",
    "fund_name": "Direxion Daily MSCI Brazil Bull 2X Shares",
    "isin": "N/A",
    "cusip": "N/A",
    "inception_date": "2025-11-29",
    "nav_amount": "0.00",
    "nav_as_of": "2025-11-29",
    "expense_ratio": "0.00",
    "ytd_return": null,
    "one_year_return": null,
    "three_year_return": null,
    "five_year_return": null,
    "ten_year_return": null,
    "since_inception_return": null,
    "asset_class": "Leveraged/Inverse",
    "region": "US",
    "market_type": "ETF",
    "distribution_yield": null,
    "distribution_frequency": "Unknown",
    "product_page_url": "https://www.direxion.com/product/brzu",
    "detail_page_url": "https://www.direxion.com/product/brzu"
  },
  {
    "ticker": "MEXX",
    "fund_name": "Direxion Daily MSCI Mexico Bull 3X Shares",
    "isin": "N/A",
    "cusip": "N/A",
    "inception_date": "2025-11-29",
    "nav_amount": "0.00",
    "nav_as_of": "2025-11-29",
    "expense_ratio": "0.00",
    "ytd_return": null,
    "one_year_return": null,
    "three_year_return": null,
    "five_year_return": null,
    "ten_year_return": null,
    "since_inception_return": null,
    "asset_class": "Leveraged/Inverse",
    "region": "US",
    "market_type": "ETF",
    "distribution_yield": null,
    "distribution_frequency": "Unknown",
    "product_page_url": "https://www.direxion.com/product/mexx",
    "detail_page_url": "https://www.direxion.com/product/mexx"
  },
  {
    "ticker": "GDXD",
    "fund_name": "Direxion Daily Gold Miners Index Bear 1X Shares",
    "isin": "N/A",
    "cusip": "N/A",
    "inception_date": "2025-11-29",
    "nav_amount": "0.00",
    "nav_as_of": "2025-11-29",
    "expense_ratio": "0.00",
    "ytd_return": null,
    "one_year_return": null,
    "three_year_return": null,
    "five_year_return": null,
    "ten_year_return": null,
    "since_inception_return": null,
    "asset_class": "Leveraged/Inverse",
    "region": "US",
    "market_type": "ETF",
    "distribution_yield": null,
    "distribution_frequency": "Unknown",
    "product_page_url": "https://www.direxion.com/product/gdxd",
    "detail_page_url": "https://www.direxion.com/product/gdxd"
  },
  {
    "ticker": "GDXU",
    "fund_name": "Direxion Daily Gold Miners Index Bull 1.25X Shares",
    "isin": "N/A",
    "cusip": "N/A",
    "inception_date": "2025-11-29",
    "nav_amount": "0.00",
    "nav_as_of": "2025-11-29",
    "expense_ratio": "0.00",
    "ytd_return": null,
    "one_year_return": null,
    "three_year_return": null,
    "five_year_return": null,
    "ten_year_return": null,
    "since_inception_return": null,
    "asset_class": "Leveraged/Inverse",
    "region": "US",
    "market_type": "ETF",
    "distribution_yield": null,
    "distribution_frequency": "Unknown",
    "product_page_url": "https://www.direxion.com/product/gdxu",
    "detail_page_url": "https://www.direxion.com/product/gdxu"
  }
]